ammg/__init__.py
ammg/ammg.py
ammg/ammg_cache.py
ammg/ammg_config.py
ammg/api_work.py
ammg/embed_metadata_to_file.py
ammg/get_apple_music_token.py
ammg-0.2.2.dist-info/METADATA
ammg-0.2.2.dist-info/WHEEL
ammg-0.2.2.dist-info/entry_points.txt
ammg-0.2.2.dist-info/licenses/LICENSE
ammg-0.2.2.dist-info/RECORD
