Metadata-Version: 2.3
Name: ammg
Version: 0.2.2
Summary: A tool for appending metadata from Apple Music to music files.
Project-URL: Homepage, https://github.com/rofe33/ammg
Project-URL: Issues, https://github.com/rofe33/ammg/issues
Author-email: Raphael Tannous <raphaeltannous@proton.me>
License:                     GNU GENERAL PUBLIC LICENSE
License-File: LICENSE
Keywords: apple music,metadata,music,mutagen
Classifier: Development Status :: 4 - Beta
Requires-Python: >=3.10
Requires-Dist: mutagen
Requires-Dist: requests
